logman/__init__.py
logman/custom_logger.py
logman/logger_factory.py
logman/formatter/__init__.py
logman/formatter/json_formatter.py
logman/formatter/plain_formatter.py
logman/handler/__init__.py
logman/handler/console_logging_handler.py
logman/handler/file_rotate_logging_handler.py
logman-0.0.3.dist-info/METADATA
logman-0.0.3.dist-info/WHEEL
logman-0.0.3.dist-info/top_level.txt
logman-0.0.3.dist-info/RECORD
